{
  "model": "mini",
  "version": "1.0.0",
  "remote_command": "none",
  "force_update": false,
  "files": [
    { "path": "app_main.py",          "target": "app_main.py" },
    { "path": "bootloader.py",        "target": "bootloader.py" },
    { "path": "boot.py",              "target": "boot.py" },
    { "path": "display_2inch.py",     "target": "display_2inch.py" },
    { "path": "writer.py",            "target": "writer.py" },
    { "path": "setup_server.py",      "target": "setup_server.py" },
    { "path": "control_poll.py",      "target": "control_poll.py" },
    { "path": "mini_digits.py",       "target": "mini_digits.py" },
    { "path": "big_digits_draw.py",   "target": "big_digits_draw.py" },
    { "path": "small_font.py",        "target": "small_font.py" },
    { "path": "age_small_font.py",    "target": "age_small_font.py" },
    { "path": "arrows_font.py",       "target": "arrows_font.py" },
    { "path": "config_font.py",       "target": "config_font.py" },
    { "path": "config_font_title.py", "target": "config_font_title.py" },
    { "path": "delta.py",             "target": "delta.py" },
    { "path": "heart.py",             "target": "heart.py" },
    { "path": "logo.bin",             "target": "logo.bin" }
  ]
}
